tencentcloud/__init__.py
tencentcloud/essbasic/__init__.py
tencentcloud/essbasic/v20201222/__init__.py
tencentcloud/essbasic/v20201222/errorcodes.py
tencentcloud/essbasic/v20201222/essbasic_client.py
tencentcloud/essbasic/v20201222/essbasic_client_async.py
tencentcloud/essbasic/v20201222/models.py
tencentcloud/essbasic/v20210526/__init__.py
tencentcloud/essbasic/v20210526/errorcodes.py
tencentcloud/essbasic/v20210526/essbasic_client.py
tencentcloud/essbasic/v20210526/essbasic_client_async.py
tencentcloud/essbasic/v20210526/models.py
tencentcloud_sdk_python_essbasic-3.1.37.dist-info/METADATA
tencentcloud_sdk_python_essbasic-3.1.37.dist-info/WHEEL
tencentcloud_sdk_python_essbasic-3.1.37.dist-info/top_level.txt
tencentcloud_sdk_python_essbasic-3.1.37.dist-info/RECORD
